scilight/__init__.py
scilight-0.6.3.dist-info/LICENSE
scilight-0.6.3.dist-info/METADATA
scilight-0.6.3.dist-info/WHEEL
scilight-0.6.3.dist-info/top_level.txt
scilight-0.6.3.dist-info/RECORD
