Metadata-Version: 2.1
Name: scilight
Version: 0.6.3
Summary: Workflow library in pure python, for executing shell commands saving data to the file system without re-executing already executed tasks.
Home-page: https://github.com/samuell/scilight
Author: Samuel Lampa
Author-email: shl@rilspace.com
License: MIT
Keywords: workflows workflow pipeline task
Classifier: Development Status :: 3 - Alpha
Classifier: Environment :: Console
Classifier: Intended Audience :: Science/Research
Classifier: License :: OSI Approved :: MIT License
Classifier: Natural Language :: English
Classifier: Operating System :: POSIX :: Linux
Classifier: Programming Language :: Python
Classifier: Programming Language :: Python :: 3
Classifier: Programming Language :: Python :: 3.6
License-File: LICENSE
